pyVoiceText.py
setup.py
pyVoiceText.egg-info/PKG-INFO
pyVoiceText.egg-info/SOURCES.txt
pyVoiceText.egg-info/dependency_links.txt
pyVoiceText.egg-info/requires.txt
pyVoiceText.egg-info/top_level.txt