Metadata-Version: 1.1
Name: pyVoiceText
Version: 0.1.0
Summary: VoiceText API wrapper
Home-page: https://github.com/who-you-me/pyVoiceText
Author: Hisao Soyama
Author-email: hisao.soyama@gmail.com
License: MIT License
Platform: UNKNOWN
Classifier: License :: OSI Approved :: MIT License
Classifier: Natural Language :: Japanese
Classifier: Programming Language :: Python :: 2
Classifier: Programming Language :: Python :: 2.7
Classifier: Topic :: Multimedia :: Sound/Audio
